mwclient_contenttranslation/__init__.py
mwclient_contenttranslation-0.1.1.post1.dist-info/LICENSE
mwclient_contenttranslation-0.1.1.post1.dist-info/METADATA
mwclient_contenttranslation-0.1.1.post1.dist-info/WHEEL
mwclient_contenttranslation-0.1.1.post1.dist-info/RECORD
