Metadata-Version: 2.1
Name: mwclient-contenttranslation
Version: 0.1.1.post1
Summary: Wikipedia ContentTranslation (CXServer) API wrapper to be used with mwclient
Author: Hung-I Wang
Author-email: whygowe@gmail.com
Requires-Python: >=3.9,<4.0
Classifier: Programming Language :: Python :: 3
Classifier: Programming Language :: Python :: 3.9
Classifier: Programming Language :: Python :: 3.10
Classifier: Programming Language :: Python :: 3.11
Requires-Dist: mwclient (>=0.10.1,<0.11.0)
Requires-Dist: requests (>=2.28.2,<3.0.0)
